{
  "curriculum": [
    {
      "grade": "9ème",
      "chapters": [
        {
          "name": "Espace",
          "exercises": ["ES1", "ES2", "ES3", "ES4", "ES5", "ES6", "ES7", "ES8", "ES9", "ES10", "ES11", "ES12", "ES13", "ES14", "ES15", "ES16", "ES17", "ES18", "ES19", "ES20", "ES21", "ES22", "ES23", "ES24", "ES25", "ES26", "ES27", "ES28", "ES29", "ES30", "ES31", "ES32", "ES33", "ES34", "ES35", "ES36", "ES37", "ES38", "ES39", "ES40", "ES41", "ES42", "ES43", "ES44", "ES45", "ES46", "ES47", "ES48", "ES49", "ES50", "ES51", "ES52", "ES53", "ES54", "ES55", "ES56", "ES57", "ES58", "ES59", "ES60", "ES61", "ES62", "ES63", "ES64", "ES65", "ES66", "ES67", "ES68", "ES69", "ES70", "ES71", "ES72", "ES73", "ES74", "ES75", "ES76", "ES77", "ES78", "ES79", "ES80", "ES81", "ES82", "ES83", "ES84", "ES85", "ES86", "ES87", "ES88", "ES89", "ES90", "ES91", "ES92", "ES93", "ES94", "ES95", "ES96", "ES97", "ES98", "ES99", "ES100", "ES101", "ES102", "ES103", "ES104", "ES105", "ES106", "ES107", "ES108", "ES109", "ES110", "ES111", "ES112", "ES113", "ES114", "ES115", "ES116", "ES117", "ES118", "ES119", "ES120", "FLPp127", "QSJp117", "FLPp137", "QSJp130", "FLPp158", "QSJp139"]
        },
        {
          "name": "Fonctions et Algèbre",
          "exercises": ["FA1", "FA2", "FA3", "FA4", "FA5", "FA6", "FA7", "FA8", "FA9", "FA10", "FA11", "FA12", "FA13", "FA14", "FA15", "FA16", "FA17", "FA18", "FA19", "FA20", "FA21", "FA22", "FA23", "FA24", "FA25", "FA26", "FA27", "FA28", "FA29", "FA30", "FA31", "FA32", "FA33", "FA34", "FA35", "FA36", "FA37", "FA38", "FA39", "FA40", "FA41", "FA42", "FA43", "FA44", "FA45", "FA46", "FA47", "FA48", "FA49", "FA50", "FA51", "FA52", "FA53", "FA54", "FA55", "FA56", "FA57", "FA58", "FA59", "FA60", "FA61", "FA62", "FA63", "FA64", "FA65", "FA66", "FA67", "FA68", "FA69", "FA70", "FA71", "FA72", "FA73", "FA74", "FA75", "FA76", "FA77", "FA78", "FA79", "FA80", "FA81", "FA82", "FA83", "FA84", "FA85", "FA86", "FA87", "FA88", "FA89", "FA90", "FA91", "FA92", "FA93", "FA94", "FA95", "FA96", "FA97", "FA98", "FA99", "FA100", "FA101", "FA102", "FA103", "FA104", "FA105", "FA106", "FA107", "FA108", "FA109", "FA110", "FA111", "FA112", "FA113", "FA114", "FA115", "FA116", "FA117", "FA118", "FA119", "FA120", "FA121", "FA122", "FA123", "FA124", "FA125", "FA126", "FA127", "FA128", "FA129", "FA130", "FA131", "FA132", "FA133", "FA134", "FA135", "FA136", "FA137", "FA138", "FA139", "FA140", "FA141", "FA142", "FA143", "FA144", "FA145", "FA146", "FA147", "FA148", "FA149", "FA150", "FA151", "FA152", "FA153", "FA154", "FA155", "FA156", "FA157", "FA158", "FA159", "FA160", "FA161", "FA162", "FA163", "FA164", "FA165", "FA166", "FA167", "FA168", "FA169", "FA170", "FA171", "FA172", "FA173", "FA174", "FA175", "FA176", "FA177", "FA178", "FA179", "FA180", "FA181", "FA182", "FA183", "FA184", "FA185", "FA186", "FA187", "FA188", "FA189", "FA190", "FA191", "FA192", "FA193", "FA194", "FA195", "FA196", "FA197", "FA198", "FA199", "FA200", "FA201", "FA202", "FA203", "FA204", "FA205", "FA206", "FA207", "FA208", "FA209", "FA210", "FA211", "FA212", "FA213", "FA214", "FA215", "FA216", "FA217", "FA218", "FA219", "FA220", "FA221", "FA222", "FA223", "FA224", "FA225", "FA226", "FA227", "FA228", "FA229", "FA230", "FA231", "FA232", "FA233", "FA234", "FA235", "FA236", "FA237", "FA238", "FA239", "FA240", "FA241", "FA242", "FA243", "FA244", "FA245", "FA246", "FA247", "FA248", "FA249", "FA250", "FA251", "FA252", "FA253", "FA254", "FA255", "FA256", "FA257", "FA258", "FA259", "FA260", "FA261", "FA262", "FA263", "FA264", "FA265", "FA266", "FA267", "FA268", "FA269", "FA270", "FA271", "FA272", "FA273", "FA274", "FA275", "FA276", "FA277", "FA278", "FA279", "FA280", "FA281", "FA282", "FA283", "FA284", "FA285", "FA286", "FA287", "FA288", "FA289", "FA290", "FA291", "FA292", "FA293", "FA294", "FA295", "FA296", "FA297", "FA298", "FA299", "FA300", "FA301", "FA302", "FA303", "FA304", "FA305", "FA306", "FA307", "FA308", "FA309", "FA310", "FA311", "FA312", "FA313", "FA314", "FA315", "FA316", "FA317", "FA318", "FA319", "FA320", "FA321", "FA322", "FA323", "FA324", "FA325", "FA326", "FA327", "FA328", "FA329", "FA330", "FA331", "FA332", "FA333", "FA334", "FA335", "FA336", "FA337", "FA338", "FA339", "FA340", "FA341", "FA342", "FA343", "FA344", "FA345", "FA346", "FA347", "FA348", "FA349", "FA350", "FA351", "FA352", "FA353", "FA354", "FA355", "FA356", "FA357", "FA358", "FA359", "FA360", "FA361", "FA362", "FA363", "FA364", "FA365", "FA366", "FA367", "FA368", "FA369", "FA370", "FA371", "FA372", "FA373", "FA374", "FA375", "FLPp39", "FLPp52", "QSJp31", "QSJp42", "FLPp64", "QSJp55", "FLPp74", "FLPp86", "FLPp92", "QSJp68", "QSJp77", "FLPp104", "FLPp105", "FLPp112", "QSJp106", "QSJp98"]
        },
        {
          "name": "Grandeurs et Mesures",
          "exercises": ["GM1", "GM2", "GM3", "GM4", "GM5", "GM6", "GM7", "GM8", "GM9", "GM10", "GM11", "GM12", "GM13", "GM14", "GM15", "GM16", "GM17", "GM18", "GM19", "GM20", "GM21", "GM22", "GM23", "GM24", "GM25", "GM26", "GM27", "GM28", "GM29", "GM30", "GM31", "GM32", "GM33", "GM34", "GM35", "GM36", "GM37", "GM38", "GM39", "GM40", "GM41", "GM42", "GM43", "GM44", "GM45", "GM46", "GM47", "GM48", "GM49", "GM50", "GM51", "GM52", "GM53", "GM54", "GM55", "GM56", "GM57", "GM58", "GM59", "GM60", "GM61", "GM62", "GM63", "GM64", "GM65", "GM66", "GM67", "GM68", "GM69", "GM70", "GM71", "GM72", "GM73", "GM74", "GM75", "GM76", "GM77", "GM78", "GM79", "GM80", "GM81", "GM82", "GM83", "GM84", "GM85", "GM86", "GM87", "GM88", "GM89", "GM90", "GM91", "GM92", "GM93", "GM94", "GM95", "GM96", "GM97", "GM98", "GM99", "GM100", "GM101", "GM102", "GM103", "GM104", "GM105", "GM106", "GM107", "GM108", "GM109", "GM110", "GM111", "GM112", "GM113", "GM114", "GM115", "GM116", "GM117", "GM118", "GM119", "GM120", "GM121", "GM122", "GM123", "GM124", "GM125", "GM126", "GM127", "GM128", "GM129", "GM130", "GM131", "GM132", "GM133", "GM134", "GM135", "GM136", "GM137", "GM138", "GM139", "GM140", "GM141", "GM142", "GM143", "GM144", "GM145", "GM146", "GM147", "GM148", "GM149", "GM150", "GM151", "GM152", "GM153", "GM154", "GM155", "GM156", "GM157", "GM158", "GM159", "GM160", "GM161", "GM162", "GM163", "GM164", "GM165", "GM166", "GM167", "GM168", "GM169", "GM170", "GM171", "GM172", "GM173", "GM174", "GM175", "GM176", "GM177", "GM178", "GM179", "GM180", "GM181", "GM182", "GM183", "GM184", "GM185", "GM186", "GM187", "GM188", "GM189", "GM190", "FLPp175", "FLPp187", "QSJp169", "QSJp173", "QSJp177", "FLPp194", "FLPp197", "QSJp191", "FLPp202", "QSJp199"]
        },
        {
          "name": "Nombres",
          "exercises": ["NO1", "NO2", "NO3", "NO4", "NO5", "NO6", "NO7", "NO8", "NO9", "NO10", "NO11", "NO12", "NO13", "NO14", "NO15", "NO16", "NO17", "NO18", "NO19", "NO20", "NO21", "NO22", "NO23", "NO24", "NO25", "NO26", "NO27", "NO28", "NO29", "NO30", "NO31", "NO32", "NO33", "NO34", "NO35", "NO36", "NO37", "NO38", "NO39", "NO40", "NO41", "NO42", "NO43", "NO44", "NO45", "NO46", "NO47", "NO48", "NO49", "NO50", "NO51", "NO52", "NO53", "NO54", "NO55", "NO56", "NO57", "NO58", "NO59", "NO60", "NO61", "NO62", "NO63", "NO64", "NO65", "NO66", "NO67", "NO68", "NO69", "NO70", "NO71", "NO72", "NO73", "NO74", "NO75", "NO76", "NO77", "NO78", "NO79", "NO80", "NO81", "NO82", "NO83", "NO84", "NO85", "NO86", "NO87", "NO88", "NO89", "NO90", "NO91", "NO92", "NO93", "NO94", "NO95", "NO96", "NO97", "NO98", "NO99", "NO100", "NO101", "NO102", "NO103", "NO104", "NO105", "NO106", "NO107", "NO108", "NO109", "NO110", "NO111", "NO112", "NO113", "NO114", "NO115", "NO116", "NO117", "NO118", "NO119", "NO120", "NO121", "NO122", "NO123", "NO124", "NO125", "NO126", "NO127", "NO128", "NO129", "NO130", "NO131", "NO132", "NO133", "NO134", "NO135", "NO136", "NO137", "NO138", "NO139", "NO140", "NO141", "NO142", "NO143", "NO144", "NO145", "NO146", "NO147", "NO148", "NO149", "NO150", "NO151", "FLPp5", "QSJp1", "FLPp15", "QSJp6", "FLPp21", "FLPp24", "QSJp18", "QSJp22"]
        },
        {
          "name": "Recherche et Stratégies",
          "exercises": ["RS1", "RS2", "RS3", "RS4", "RS5", "RS6", "RS7", "RS8", "RS9", "RS10", "RS11", "RS12", "RS13", "RS14", "RS15", "RS16", "RS17", "RS18", "RS19", "RS20", "RS21", "RS22", "RS23", "RS24", "RS25"]
        }
      ]
    },
    
    {
      "grade": "10ème",
      "chapters": [
        {
          "name": "Espace",
          "exercises": ["ES1", "ES2", "ES3", "ES4", "ES5", "ES6", "ES7", "ES8", "ES9", "ES10", "ES11", "ES12", "ES13", "ES14", "ES15", "ES16", "ES17", "ES18", "ES19", "ES20", "ES21", "ES22", "ES23", "ES24", "ES25", "ES26", "ES27", "ES28", "ES29", "ES30", "ES31", "ES32", "ES33", "ES34", "ES35", "ES36", "ES37", "ES38", "ES39", "ES40", "ES41", "ES42", "ES43", "ES44", "ES45", "ES46", "ES47", "ES48", "ES49", "ES50", "ES51", "ES52", "ES53", "ES54", "ES55", "ES56", "ES57", "ES58", "ES59", "ES60", "ES61", "ES62", "ES63", "ES64", "ES65", "ES66", "ES67", "ES68", "ES69", "ES70", "ES71", "ES72", "ES73", "ES74", "ES75", "ES76", "ES77", "ES78", "ES79", "ES80", "ES81", "ES82", "ES83", "ES84", "ES85", "ES86", "ES87", "ES88", "ES89", "ES90", "ES91", "ES92", "ES93", "ES94", "ES95", "ES96", "ES97", "ES98", "ES99", "ES100", "ES101", "ES102", "ES103", "ES104", "ES105", "ES106", "ES107", "ES108", "ES109", "ES110", "ES111", "ES112", "ES113", "ES114", "ES115", "ES116", "ES117", "ES118", "ES119", "ES120", "FLPp127", "QSJp117", "FLPp137", "QSJp130", "FLPp158", "QSJp139"]
        },
        {
          "name": "Fonctions et Algèbre",
          "exercises": ["FA1", "FA2", "FA3", "FA4", "FA5", "FA6", "FA7", "FA8", "FA9", "FA10", "FA11", "FA12", "FA13", "FA14", "FA15", "FA16", "FA17", "FA18", "FA19", "FA20", "FA21", "FA22", "FA23", "FA24", "FA25", "FA26", "FA27", "FA28", "FA29", "FA30", "FA31", "FA32", "FA33", "FA34", "FA35", "FA36", "FA37", "FA38", "FA39", "FA40", "FA41", "FA42", "FA43", "FA44", "FA45", "FA46", "FA47", "FA48", "FA49", "FA50", "FA51", "FA52", "FA53", "FA54", "FA55", "FA56", "FA57", "FA58", "FA59", "FA60", "FA61", "FA62", "FA63", "FA64", "FA65", "FA66", "FA67", "FA68", "FA69", "FA70", "FA71", "FA72", "FA73", "FA74", "FA75", "FA76", "FA77", "FA78", "FA79", "FA80", "FA81", "FA82", "FA83", "FA84", "FA85", "FA86", "FA87", "FA88", "FA89", "FA90", "FA91", "FA92", "FA93", "FA94", "FA95", "FA96", "FA97", "FA98", "FA99", "FA100", "FA101", "FA102", "FA103", "FA104", "FA105", "FA106", "FA107", "FA108", "FA109", "FA110", "FA111", "FA112", "FA113", "FA114", "FA115", "FA116", "FA117", "FA118", "FA119", "FA120", "FA121", "FA122", "FA123", "FA124", "FA125", "FA126", "FA127", "FA128", "FA129", "FA130", "FA131", "FA132", "FA133", "FA134", "FA135", "FA136", "FA137", "FA138", "FA139", "FA140", "FA141", "FA142", "FA143", "FA144", "FA145", "FA146", "FA147", "FA148", "FA149", "FA150", "FA151", "FA152", "FA153", "FA154", "FA155", "FA156", "FA157", "FA158", "FA159", "FA160", "FA161", "FA162", "FA163", "FA164", "FA165", "FA166", "FA167", "FA168", "FA169", "FA170", "FA171", "FA172", "FA173", "FA174", "FA175", "FA176", "FA177", "FA178", "FA179", "FA180", "FA181", "FA182", "FA183", "FA184", "FA185", "FA186", "FA187", "FA188", "FA189", "FA190", "FA191", "FA192", "FA193", "FA194", "FA195", "FA196", "FA197", "FA198", "FA199", "FA200", "FA201", "FA202", "FA203", "FA204", "FA205", "FA206", "FA207", "FA208", "FA209", "FA210", "FA211", "FA212", "FA213", "FA214", "FA215", "FA216", "FA217", "FA218", "FA219", "FA220", "FA221", "FA222", "FA223", "FA224", "FA225", "FA226", "FA227", "FA228", "FA229", "FA230", "FA231", "FA232", "FA233", "FA234", "FA235", "FA236", "FA237", "FA238", "FA239", "FA240", "FA241", "FA242", "FA243", "FA244", "FA245", "FA246", "FA247", "FA248", "FA249", "FA250", "FA251", "FA252", "FA253", "FA254", "FA255", "FA256", "FA257", "FA258", "FA259", "FA260", "FA261", "FA262", "FA263", "FA264", "FA265", "FA266", "FA267", "FA268", "FA269", "FA270", "FA271", "FA272", "FA273", "FA274", "FA275", "FA276", "FA277", "FA278", "FA279", "FA280", "FA281", "FA282", "FA283", "FA284", "FA285", "FA286", "FA287", "FA288", "FA289", "FA290", "FA291", "FA292", "FA293", "FA294", "FA295", "FA296", "FA297", "FA298", "FA299", "FA300", "FA301", "FA302", "FA303", "FA304", "FA305", "FA306", "FA307", "FA308", "FA309", "FA310", "FA311", "FA312", "FA313", "FA314", "FA315", "FA316", "FA317", "FA318", "FA319", "FA320", "FA321", "FA322", "FA323", "FA324", "FA325", "FA326", "FA327", "FA328", "FA329", "FA330", "FA331", "FA332", "FA333", "FA334", "FA335", "FA336", "FA337", "FA338", "FA339", "FA340", "FA341", "FA342", "FA343", "FA344", "FA345", "FA346", "FA347", "FA348", "FA349", "FA350", "FA351", "FA352", "FA353", "FA354", "FA355", "FA356", "FA357", "FA358", "FA359", "FA360", "FA361", "FA362", "FA363", "FA364", "FA365", "FA366", "FA367", "FA368", "FA369", "FA370", "FA371", "FA372", "FA373", "FA374", "FA375", "FLPp39", "FLPp52", "QSJp31", "QSJp42", "FLPp64", "QSJp55", "FLPp74", "FLPp86", "FLPp92", "QSJp68", "QSJp77", "FLPp104", "FLPp105", "FLPp112", "QSJp106", "QSJp98"]
        },
        {
          "name": "Grandeurs et Mesures",
          "exercises": ["GM1", "GM2", "GM3", "GM4", "GM5", "GM6", "GM7", "GM8", "GM9", "GM10", "GM11", "GM12", "GM13", "GM14", "GM15", "GM16", "GM17", "GM18", "GM19", "GM20", "GM21", "GM22", "GM23", "GM24", "GM25", "GM26", "GM27", "GM28", "GM29", "GM30", "GM31", "GM32", "GM33", "GM34", "GM35", "GM36", "GM37", "GM38", "GM39", "GM40", "GM41", "GM42", "GM43", "GM44", "GM45", "GM46", "GM47", "GM48", "GM49", "GM50", "GM51", "GM52", "GM53", "GM54", "GM55", "GM56", "GM57", "GM58", "GM59", "GM60", "GM61", "GM62", "GM63", "GM64", "GM65", "GM66", "GM67", "GM68", "GM69", "GM70", "GM71", "GM72", "GM73", "GM74", "GM75", "GM76", "GM77", "GM78", "GM79", "GM80", "GM81", "GM82", "GM83", "GM84", "GM85", "GM86", "GM87", "GM88", "GM89", "GM90", "GM91", "GM92", "GM93", "GM94", "GM95", "GM96", "GM97", "GM98", "GM99", "GM100", "GM101", "GM102", "GM103", "GM104", "GM105", "GM106", "GM107", "GM108", "GM109", "GM110", "GM111", "GM112", "GM113", "GM114", "GM115", "GM116", "GM117", "GM118", "GM119", "GM120", "GM121", "GM122", "GM123", "GM124", "GM125", "GM126", "GM127", "GM128", "GM129", "GM130", "GM131", "GM132", "GM133", "GM134", "GM135", "GM136", "GM137", "GM138", "GM139", "GM140", "GM141", "GM142", "GM143", "GM144", "GM145", "GM146", "GM147", "GM148", "GM149", "GM150", "GM151", "GM152", "GM153", "GM154", "GM155", "GM156", "GM157", "GM158", "GM159", "GM160", "GM161", "GM162", "GM163", "GM164", "GM165", "GM166", "GM167", "GM168", "GM169", "GM170", "GM171", "GM172", "GM173", "GM174", "GM175", "GM176", "GM177", "GM178", "GM179", "GM180", "GM181", "GM182", "GM183", "GM184", "GM185", "GM186", "GM187", "GM188", "GM189", "GM190", "FLPp175", "FLPp187", "QSJp169", "QSJp173", "QSJp177", "FLPp194", "FLPp197", "QSJp191", "FLPp202", "QSJp199"]
        },
        {
          "name": "Nombres",
          "exercises": ["NO1", "NO2", "NO3", "NO4", "NO5", "NO6", "NO7", "NO8", "NO9", "NO10", "NO11", "NO12", "NO13", "NO14", "NO15", "NO16", "NO17", "NO18", "NO19", "NO20", "NO21", "NO22", "NO23", "NO24", "NO25", "NO26", "NO27", "NO28", "NO29", "NO30", "NO31", "NO32", "NO33", "NO34", "NO35", "NO36", "NO37", "NO38", "NO39", "NO40", "NO41", "NO42", "NO43", "NO44", "NO45", "NO46", "NO47", "NO48", "NO49", "NO50", "NO51", "NO52", "NO53", "NO54", "NO55", "NO56", "NO57", "NO58", "NO59", "NO60", "NO61", "NO62", "NO63", "NO64", "NO65", "NO66", "NO67", "NO68", "NO69", "NO70", "NO71", "NO72", "NO73", "NO74", "NO75", "NO76", "NO77", "NO78", "NO79", "NO80", "NO81", "NO82", "NO83", "NO84", "NO85", "NO86", "NO87", "NO88", "NO89", "NO90", "NO91", "NO92", "NO93", "NO94", "NO95", "NO96", "NO97", "NO98", "NO99", "NO100", "NO101", "NO102", "NO103", "NO104", "NO105", "NO106", "NO107", "NO108", "NO109", "NO110", "NO111", "NO112", "NO113", "NO114", "NO115", "NO116", "NO117", "NO118", "NO119", "NO120", "NO121", "NO122", "NO123", "NO124", "NO125", "NO126", "NO127", "NO128", "NO129", "NO130", "NO131", "NO132", "NO133", "NO134", "NO135", "NO136", "NO137", "NO138", "NO139", "NO140", "NO141", "NO142", "NO143", "NO144", "NO145", "NO146", "NO147", "NO148", "NO149", "NO150", "NO151", "FLPp5", "QSJp1", "FLPp15", "QSJp6", "FLPp21", "FLPp24", "QSJp18", "QSJp22"]
        },
        {
          "name": "Recherche et Stratégies",
          "exercises": ["RS1", "RS2", "RS3", "RS4", "RS5", "RS6", "RS7", "RS8", "RS9", "RS10", "RS11", "RS12", "RS13", "RS14", "RS15", "RS16", "RS17", "RS18", "RS19", "RS20", "RS21", "RS22", "RS23", "RS24", "RS25"]
        }
      ]
    },
    {
      "grade": "11ème",
      "chapters": [
        {
          "name": "Espace",
          "exercises": ["ES1", "ES2", "ES3", "ES4", "ES5", "ES6", "ES7", "ES8", "ES9", "ES10", "ES11", "ES12", "ES13", "ES14", "ES15", "ES16", "ES17", "ES18", "ES19", "ES20", "ES21", "ES22", "ES23", "ES24", "ES25", "ES26", "ES27", "ES28", "ES29", "ES30", "ES31", "ES32", "ES33", "ES34", "ES35", "ES36", "ES37", "ES38", "ES39", "ES40", "ES41", "ES42", "ES43", "ES44", "ES45", "ES46", "ES47", "ES48", "ES49", "ES50", "ES51", "ES52", "ES53", "ES54", "ES55", "ES56", "ES57", "ES58", "ES59", "ES60", "ES61", "ES62", "ES63", "ES64", "ES65", "ES66", "ES67", "ES68", "ES69", "ES70", "ES71", "ES72", "ES73", "ES74", "ES75", "ES76", "ES77", "ES78", "ES79", "ES80", "ES81", "ES82", "ES83", "ES84", "ES85", "ES86", "ES87", "ES88", "ES89", "ES90", "ES91", "ES92", "ES93", "ES94", "ES95", "ES96", "ES97", "ES98", "ES99", "ES100", "ES101", "ES102", "ES103", "ES104", "ES105", "ES106", "ES107", "ES108", "ES109", "ES110", "ES111", "ES112", "ES113", "ES114", "ES115", "ES116", "ES117", "ES118", "ES119", "ES120", "FLPp127", "QSJp117", "FLPp137", "QSJp130", "FLPp158", "QSJp139"]
        },
        {
          "name": "Fonctions et Algèbre",
          "exercises": ["FA1", "FA2", "FA3", "FA4", "FA5", "FA6", "FA7", "FA8", "FA9", "FA10", "FA11", "FA12", "FA13", "FA14", "FA15", "FA16", "FA17", "FA18", "FA19", "FA20", "FA21", "FA22", "FA23", "FA24", "FA25", "FA26", "FA27", "FA28", "FA29", "FA30", "FA31", "FA32", "FA33", "FA34", "FA35", "FA36", "FA37", "FA38", "FA39", "FA40", "FA41", "FA42", "FA43", "FA44", "FA45", "FA46", "FA47", "FA48", "FA49", "FA50", "FA51", "FA52", "FA53", "FA54", "FA55", "FA56", "FA57", "FA58", "FA59", "FA60", "FA61", "FA62", "FA63", "FA64", "FA65", "FA66", "FA67", "FA68", "FA69", "FA70", "FA71", "FA72", "FA73", "FA74", "FA75", "FA76", "FA77", "FA78", "FA79", "FA80", "FA81", "FA82", "FA83", "FA84", "FA85", "FA86", "FA87", "FA88", "FA89", "FA90", "FA91", "FA92", "FA93", "FA94", "FA95", "FA96", "FA97", "FA98", "FA99", "FA100", "FA101", "FA102", "FA103", "FA104", "FA105", "FA106", "FA107", "FA108", "FA109", "FA110", "FA111", "FA112", "FA113", "FA114", "FA115", "FA116", "FA117", "FA118", "FA119", "FA120", "FA121", "FA122", "FA123", "FA124", "FA125", "FA126", "FA127", "FA128", "FA129", "FA130", "FA131", "FA132", "FA133", "FA134", "FA135", "FA136", "FA137", "FA138", "FA139", "FA140", "FA141", "FA142", "FA143", "FA144", "FA145", "FA146", "FA147", "FA148", "FA149", "FA150", "FA151", "FA152", "FA153", "FA154", "FA155", "FA156", "FA157", "FA158", "FA159", "FA160", "FA161", "FA162", "FA163", "FA164", "FA165", "FA166", "FA167", "FA168", "FA169", "FA170", "FA171", "FA172", "FA173", "FA174", "FA175", "FA176", "FA177", "FA178", "FA179", "FA180", "FA181", "FA182", "FA183", "FA184", "FA185", "FA186", "FA187", "FA188", "FA189", "FA190", "FA191", "FA192", "FA193", "FA194", "FA195", "FA196", "FA197", "FA198", "FA199", "FA200", "FA201", "FA202", "FA203", "FA204", "FA205", "FA206", "FA207", "FA208", "FA209", "FA210", "FA211", "FA212", "FA213", "FA214", "FA215", "FA216", "FA217", "FA218", "FA219", "FA220", "FA221", "FA222", "FA223", "FA224", "FA225", "FA226", "FA227", "FA228", "FA229", "FA230", "FA231", "FA232", "FA233", "FA234", "FA235", "FA236", "FA237", "FA238", "FA239", "FA240", "FA241", "FA242", "FA243", "FA244", "FA245", "FA246", "FA247", "FA248", "FA249", "FA250", "FA251", "FA252", "FA253", "FA254", "FA255", "FA256", "FA257", "FA258", "FA259", "FA260", "FA261", "FA262", "FA263", "FA264", "FA265", "FA266", "FA267", "FA268", "FA269", "FA270", "FA271", "FA272", "FA273", "FA274", "FA275", "FA276", "FA277", "FA278", "FA279", "FA280", "FA281", "FA282", "FA283", "FA284", "FA285", "FA286", "FA287", "FA288", "FA289", "FA290", "FA291", "FA292", "FA293", "FA294", "FA295", "FA296", "FA297", "FA298", "FA299", "FA300", "FA301", "FA302", "FA303", "FA304", "FA305", "FA306", "FA307", "FA308", "FA309", "FA310", "FA311", "FA312", "FA313", "FA314", "FA315", "FA316", "FA317", "FA318", "FA319", "FA320", "FA321", "FA322", "FA323", "FA324", "FA325", "FA326", "FA327", "FA328", "FA329", "FA330", "FA331", "FA332", "FA333", "FA334", "FA335", "FA336", "FA337", "FA338", "FA339", "FA340", "FA341", "FA342", "FA343", "FA344", "FA345", "FA346", "FA347", "FA348", "FA349", "FA350", "FA351", "FA352", "FA353", "FA354", "FA355", "FA356", "FA357", "FA358", "FA359", "FA360", "FA361", "FA362", "FA363", "FA364", "FA365", "FA366", "FA367", "FA368", "FA369", "FA370", "FA371", "FA372", "FA373", "FA374", "FA375", "FLPp39", "FLPp52", "QSJp31", "QSJp42", "FLPp64", "QSJp55", "FLPp74", "FLPp86", "FLPp92", "QSJp68", "QSJp77", "FLPp104", "FLPp105", "FLPp112", "QSJp106", "QSJp98"]
        },
        {
          "name": "Grandeurs et Mesures",
          "exercises": ["GM1", "GM2", "GM3", "GM4", "GM5", "GM6", "GM7", "GM8", "GM9", "GM10", "GM11", "GM12", "GM13", "GM14", "GM15", "GM16", "GM17", "GM18", "GM19", "GM20", "GM21", "GM22", "GM23", "GM24", "GM25", "GM26", "GM27", "GM28", "GM29", "GM30", "GM31", "GM32", "GM33", "GM34", "GM35", "GM36", "GM37", "GM38", "GM39", "GM40", "GM41", "GM42", "GM43", "GM44", "GM45", "GM46", "GM47", "GM48", "GM49", "GM50", "GM51", "GM52", "GM53", "GM54", "GM55", "GM56", "GM57", "GM58", "GM59", "GM60", "GM61", "GM62", "GM63", "GM64", "GM65", "GM66", "GM67", "GM68", "GM69", "GM70", "GM71", "GM72", "GM73", "GM74", "GM75", "GM76", "GM77", "GM78", "GM79", "GM80", "GM81", "GM82", "GM83", "GM84", "GM85", "GM86", "GM87", "GM88", "GM89", "GM90", "GM91", "GM92", "GM93", "GM94", "GM95", "GM96", "GM97", "GM98", "GM99", "GM100", "GM101", "GM102", "GM103", "GM104", "GM105", "GM106", "GM107", "GM108", "GM109", "GM110", "GM111", "GM112", "GM113", "GM114", "GM115", "GM116", "GM117", "GM118", "GM119", "GM120", "GM121", "GM122", "GM123", "GM124", "GM125", "GM126", "GM127", "GM128", "GM129", "GM130", "GM131", "GM132", "GM133", "GM134", "GM135", "GM136", "GM137", "GM138", "GM139", "GM140", "GM141", "GM142", "GM143", "GM144", "GM145", "GM146", "GM147", "GM148", "GM149", "GM150", "GM151", "GM152", "GM153", "GM154", "GM155", "GM156", "GM157", "GM158", "GM159", "GM160", "GM161", "GM162", "GM163", "GM164", "GM165", "GM166", "GM167", "GM168", "GM169", "GM170", "GM171", "GM172", "GM173", "GM174", "GM175", "GM176", "GM177", "GM178", "GM179", "GM180", "GM181", "GM182", "GM183", "GM184", "GM185", "GM186", "GM187", "GM188", "GM189", "GM190", "FLPp175", "FLPp187", "QSJp169", "QSJp173", "QSJp177", "FLPp194", "FLPp197", "QSJp191", "FLPp202", "QSJp199"]
        },
        {
          "name": "Nombres",
          "exercises": ["NO1", "NO2", "NO3", "NO4", "NO5", "NO6", "NO7", "NO8", "NO9", "NO10", "NO11", "NO12", "NO13", "NO14", "NO15", "NO16", "NO17", "NO18", "NO19", "NO20", "NO21", "NO22", "NO23", "NO24", "NO25", "NO26", "NO27", "NO28", "NO29", "NO30", "NO31", "NO32", "NO33", "NO34", "NO35", "NO36", "NO37", "NO38", "NO39", "NO40", "NO41", "NO42", "NO43", "NO44", "NO45", "NO46", "NO47", "NO48", "NO49", "NO50", "NO51", "NO52", "NO53", "NO54", "NO55", "NO56", "NO57", "NO58", "NO59", "NO60", "NO61", "NO62", "NO63", "NO64", "NO65", "NO66", "NO67", "NO68", "NO69", "NO70", "NO71", "NO72", "NO73", "NO74", "NO75", "NO76", "NO77", "NO78", "NO79", "NO80", "NO81", "NO82", "NO83", "NO84", "NO85", "NO86", "NO87", "NO88", "NO89", "NO90", "NO91", "NO92", "NO93", "NO94", "NO95", "NO96", "NO97", "NO98", "NO99", "NO100", "NO101", "NO102", "NO103", "NO104", "NO105", "NO106", "NO107", "NO108", "NO109", "NO110", "NO111", "NO112", "NO113", "NO114", "NO115", "NO116", "NO117", "NO118", "NO119", "NO120", "NO121", "NO122", "NO123", "NO124", "NO125", "NO126", "NO127", "NO128", "NO129", "NO130", "NO131", "NO132", "NO133", "NO134", "NO135", "NO136", "NO137", "NO138", "NO139", "NO140", "NO141", "NO142", "NO143", "NO144", "NO145", "NO146", "NO147", "NO148", "NO149", "NO150", "NO151", "FLPp5", "QSJp1", "FLPp15", "QSJp6", "FLPp21", "FLPp24", "QSJp18", "QSJp22"]
        },
        {
          "name": "Recherche et Stratégies",
          "exercises": ["RS1", "RS2", "RS3", "RS4", "RS5", "RS6", "RS7", "RS8", "RS9", "RS10", "RS11", "RS12", "RS13", "RS14", "RS15", "RS16", "RS17", "RS18", "RS19", "RS20", "RS21", "RS22", "RS23", "RS24", "RS25"]
        }
      ]
    }
  ]
}